project_1.srcs/sources_1/new/mealy.v
`timescale 1ns / 1ps
//////////////////////////////////////////////////////////////////////////////////
// Company: 
// Engineer: 
// 
// Create Date: 10/13/2025 11:22:16 AM
// Design Name: 
// Module Name: mealy
// Project Name: 
// Target Devices: 
// Tool Versions: 
// Description: 
// 
// Dependencies: 
// 
// Revision:
// Revision 0.01 - File Created
// Additional Comments:
// 
//////////////////////////////////////////////////////////////////////////////////


module mealy(
input REQ,
input RW,
input CLK,
input RESET,
input MEM_READY,
output reg MEM_EN,
output reg DATA_EN,
output reg DONE
    );

// state encoding
localparam IDLE = 2'b00;
localparam ACCESS = 2'b01;
localparam DONE_STATE = 2'b10;
reg[1:0] state, next_state;

// next state
always @(*) begin
    case(state)
        IDLE: begin
            if(REQ)
                next_state = ACCESS;
            else
                next_state = IDLE;
        end
        ACCESS: begin
            if(MEM_READY)
                next_state = DONE_STATE;
            else
                next_state = ACCESS;
        end
        DONE_STATE: begin
            next_state = IDLE;
        end
    endcase
end

// output logic
always @(*) begin
    MEM_EN = 0;
    DATA_EN = 0;
    DONE = 0;
    case(state)
        IDLE: begin
            if(REQ)begin
                MEM_EN = 1;
                DATA_EN = 1;
            end
        end
        ACCESS: begin
            MEM_EN = 1;
            DATA_EN = 1;
            if(MEM_READY)
                DONE = 1;
        end
        DONE_STATE: DONE = 1;
    endcase
end

// state register
always @(posedge CLK or posedge RESET) begin
    if(RESET)
        state <= IDLE;
    else
        state <= next_state;
end
   
endmodule

project_1.srcs/sources_1/new/moore.v
`timescale 1ns / 1ps
//////////////////////////////////////////////////////////////////////////////////
// Company: 
// Engineer: 
// 
// Create Date: 10/13/2025 11:22:16 AM
// Design Name: 
// Module Name: moore
// Project Name: 
// Target Devices: 
// Tool Versions: 
// Description: 
// 
// Dependencies: 
// 
// Revision:
// Revision 0.01 - File Created
// Additional Comments:
// 
//////////////////////////////////////////////////////////////////////////////////


module moore(
input REQ,
input RW,
input CLK,
input RESET,
input MEM_READY,
output reg MEM_EN,
output reg DATA_EN,
output reg DONE
    );

// state encoding
localparam IDLE = 2'b00;
localparam READ = 2'b01;
localparam WRITE = 2'b10;
localparam DONE_STATE = 2'b11;

reg[1:0] state, next_state;

// next state
always @(*) begin
    case(state)
        IDLE: begin
            if(REQ && !RW)
                next_state = READ;
            else if(REQ && RW==1)
                next_state = WRITE;
            else
                next_state = IDLE;
        end
        READ: begin
            if(MEM_READY)
                next_state = DONE_STATE;
            else
                next_state = READ;
        end
        WRITE: begin
            if(MEM_READY)
                next_state = DONE_STATE;
            else
                next_state = WRITE; 
        end
        DONE_STATE: begin
            if(!REQ)
                next_state = IDLE;
            else
                next_state = DONE_STATE;
        end
    endcase
end

// output logic
always @(*) begin
    case(state)
        IDLE: begin
            MEM_EN = 0;
            DATA_EN = 0;
            DONE = 0;
        end
        READ: begin
            MEM_EN = 1;
            DATA_EN = 1;
            DONE = 0;
        end
        WRITE: begin
            MEM_EN = 1;
            DATA_EN = 1;
            DONE = 0;
        end 
        DONE_STATE: begin
            MEM_EN = 0;
            DATA_EN = 0;
            DONE = 1;
        end
    endcase
end

// state register
always @(posedge CLK or posedge RESET) begin
    if(RESET)
        state <= IDLE;
    else
        state <= next_state;
end

endmodule

project_1.srcs/sim_1/new/tb_controller.v
`timescale 1ns / 1ps
module tb_fsm_deterministic;

    // Inputs
    reg CLK, RESET, REQ, RW, MEM_READY;

    // Outputs
    wire MEM_EN_moore, DATA_EN_moore, DONE_moore;
    wire MEM_EN_mealy, DATA_EN_mealy, DONE_mealy;

    // Clock parameters
    parameter CLK_PERIOD = 10;

    // Clock generation
    always #(CLK_PERIOD/2) CLK = ~CLK;

    // Instantiate DUTs
    moore uut_moore (
        .REQ(REQ), .RW(RW), .CLK(CLK), .RESET(RESET),
        .MEM_READY(MEM_READY),
        .MEM_EN(MEM_EN_moore), .DATA_EN(DATA_EN_moore), .DONE(DONE_moore)
    );

    mealy uut_mealy (
        .REQ(REQ), .RW(RW), .CLK(CLK), .RESET(RESET),
        .MEM_READY(MEM_READY),
        .MEM_EN(MEM_EN_mealy), .DATA_EN(DATA_EN_mealy), .DONE(DONE_mealy)
    );

    //----------------------------------------------------------------------
    // Helper tasks for clean deterministic stimulus
    //----------------------------------------------------------------------

    // Apply synchronous reset
    task do_reset;
        begin
            RESET = 1;
            #(3*CLK_PERIOD);
            RESET = 0;
        end
    endtask

    // Deterministic test sequence for read and write operations
    task do_transaction(input RW_mode, input integer ready_delay, input integer hold_time);
        begin
            RW = RW_mode;
            REQ = 1;
            MEM_READY = 0;

            // Wait before memory becomes ready
            #(ready_delay);
            MEM_READY = 1;

            // Hold REQ and READY high for defined time
            #(hold_time);
            REQ = 0;
            MEM_READY = 0;
        end
    endtask

    //----------------------------------------------------------------------
    // Main deterministic sequence
    //----------------------------------------------------------------------

    initial begin
        // VCD dump for waveform inspection
        $dumpfile("fsm_deterministic.vcd");
        $dumpvars(0, tb_fsm_deterministic);

        // Initialize
        CLK = 0; RESET = 0; REQ = 0; RW = 0; MEM_READY = 0;

        do_reset();

        $display("\n=== Starting Deterministic FSM Timing Test ===\n");

        // Test 1: READ - memory ready quickly after REQ
        $display("\n-- Test 1: READ (fast memory) --");
        do_transaction(0, 2*CLK_PERIOD, 5*CLK_PERIOD);

        // Test 2: WRITE - memory ready delayed
        $display("\n-- Test 2: WRITE (slow memory) --");
        do_transaction(1, 8*CLK_PERIOD, 3*CLK_PERIOD);

        // Test 3: READ - memory ready coincides exactly with rising CLK edge
        $display("\n-- Test 3: READ (ready aligns with clock edge) --");
        REQ = 1; RW = 0; MEM_READY = 0;
        #(CLK_PERIOD - 1); MEM_READY = 1;  // Just before clock edge
        #(2*CLK_PERIOD);
        REQ = 0; MEM_READY = 0;

        // Test 4: WRITE - MEM_READY glitch before actual ready
        $display("\n-- Test 4: WRITE (ready glitch before valid) --");
        REQ = 1; RW = 1;
        MEM_READY = 1; #(CLK_PERIOD/3); MEM_READY = 0; // glitch
        #(4*CLK_PERIOD); MEM_READY = 1; #(CLK_PERIOD);
        REQ = 0; MEM_READY = 0;

        // Test 5: READ - back-to-back transactions (stress timing recovery)
        $display("\n-- Test 5: Back-to-back READs --");
        do_transaction(0, 4*CLK_PERIOD, 3*CLK_PERIOD);
        #(2*CLK_PERIOD);
        do_transaction(0, 1*CLK_PERIOD, 3*CLK_PERIOD);

        // Done
        #(10*CLK_PERIOD);
        $display("\n=== Simulation Complete ===\n");
        $finish;
    end

    //----------------------------------------------------------------------
    // Continuous monitoring for timing analysis
    //----------------------------------------------------------------------
    initial begin
        $display("  TIME | REQ RW MEM_READY || Moore: MEM_EN DATA_EN DONE || Mealy: MEM_EN DATA_EN DONE");
        $display("---------------------------------------------------------------------------------------");
        $monitor("%6t |  %b   %b     %b     ||   %b      %b      %b   ||   %b      %b      %b",
                 $time, REQ, RW, MEM_READY,
                 MEM_EN_moore, DATA_EN_moore, DONE_moore,
                 MEM_EN_mealy, DATA_EN_mealy, DONE_mealy);
    end

endmodule

project_1.sim/sim_1/behav/xsim/fsm_deterministic.vcd
$date
   Mon Oct 13 15:31:06 2025
$end

$version
  2025.1.0
  $dumpfile ("fsm_deterministic.vcd") 
$end

$timescale
  1ps
$end

$scope module tb_fsm_deterministic $end
$var reg 1 ! CLK $end
$var reg 1 " RESET $end
$var reg 1 # REQ $end
$var reg 1 $ RW $end
$var reg 1 % MEM_READY $end
$var wire 1 & MEM_EN_moore $end
$var wire 1 ' DATA_EN_moore $end
$var wire 1 ( DONE_moore $end
$var wire 1 ) MEM_EN_mealy $end
$var wire 1 * DATA_EN_mealy $end
$var wire 1 + DONE_mealy $end
$scope module uut_moore $end
$var wire 1 , REQ $end
$var wire 1 - RW $end
$var wire 1 . CLK $end
$var wire 1 / RESET $end
$var wire 1 0 MEM_READY $end
$var reg 1 1 MEM_EN $end
$var reg 1 2 DATA_EN $end
$var reg 1 3 DONE $end
$var reg 2 4 state [1:0] $end
$var reg 2 5 next_state [1:0] $end
$upscope $end
$scope module uut_mealy $end
$var wire 1 6 REQ $end
$var wire 1 7 RW $end
$var wire 1 8 CLK $end
$var wire 1 9 RESET $end
$var wire 1 : MEM_READY $end
$var reg 1 ; MEM_EN $end
$var reg 1 < DATA_EN $end
$var reg 1 = DONE $end
$var reg 2 > state [1:0] $end
$var reg 2 ? next_state [1:0] $end
$upscope $end
$scope task do_reset $end
$upscope $end
$scope task do_transaction $end
$var reg 1 @ RW_mode $end
$var integer 32 A ready_delay [31:0] $end
$var integer 32 B hold_time [31:0] $end
$upscope $end
$upscope $end
$enddefinitions $end

#0
$dumpvars
0!
1"
0#
0$
0%
0&
0'
0(
0)
0*
0+
0,
0-
0.
1/
00
01
02
03
b0 4
b0 5
06
07
08
19
0:
0;
0<
0=
b0 >
b0 ?
x@
bx A
bx B
$end

#5000
1!
1.
18

#10000
0!
0.
08

#15000
1!
1.
18

#20000
0!
0.
08

#25000
1!
1.
18

#30000
0!
0"
1#
1)
1*
1,
0.
0/
b1 5
16
08
09
1;
1<
b1 ?
0@
b10100 A
b110010 B

#35000
1!
1&
1'
1.
11
12
b1 4
18
1;
1<
b1 >

#40000
0!
0.
08

#45000
1!
1.
18

#50000
0!
1%
1+
0.
10
b11 5
08
1:
1;
1<
1=
b10 ?

#55000
1!
0&
0'
1(
0)
0*
1.
01
02
13
b11 4
18
0;
0<
1=
b10 >
b0 ?

#60000
0!
0.
08

#65000
1!
1)
1*
0+
1.
18
1;
1<
0=
b0 >
b1 ?

#70000
0!
0.
08

#75000
1!
1+
1.
18
1;
1<
1=
b1 >
b10 ?

#80000
0!
0.
08

#85000
1!
0)
0*
1.
18
0;
0<
1=
b10 >
b0 ?

#90000
0!
0.
08

#95000
1!
1)
1*
0+
1.
18
1;
1<
0=
b0 >
b1 ?

#100000
0!
1#
1$
0%
1-
0.
00
17
08
0:
1;
1<
1@
b1010000 A
b11110 B

#105000
1!
1.
18
1;
1<
b1 >

#110000
0!
0.
08

#115000
1!
1.
18

#120000
0!
0.
08

#125000
1!
1.
18

#130000
0!
0.
08

#135000
1!
1.
18

#140000
0!
0.
08

#145000
1!
1.
18

#150000
0!
0.
08

#155000
1!
1.
18

#160000
0!
0.
08

#165000
1!
1.
18

#170000
0!
0.
08

#175000
1!
1.
18

#180000
0!
1%
1+
0.
10
08
1:
1;
1<
1=
b10 ?

#185000
1!
0)
0*
1.
18
0;
0<
1=
b10 >
b0 ?

#190000
0!
0.
08

#195000
1!
1)
1*
0+
1.
18
1;
1<
0=
b0 >
b1 ?

#200000
0!
0.
08

#205000
1!
1+
1.
18
1;
1<
1=
b1 >
b10 ?

#210000
0!
1#
0$
0%
0+
0-
0.
00
07
08
0:
1;
1<
0=
b1 ?

#215000
1!
1.
18

#219000
1%
1+
10
1:
1;
1<
1=
b10 ?

#220000
0!
0.
08

#225000
1!
0)
0*
1.
18
0;
0<
1=
b10 >
b0 ?

#230000
0!
0.
08

#235000
1!
1)
1*
0+
1.
18
1;
1<
0=
b0 >
b1 ?

#239000
1#
1$
1%
1-
17

#240000
0!
0.
08

#242000
0%
00
0:
1;
1<

#245000
1!
1.
18
1;
1<
b1 >

#250000
0!
0.
08

#255000
1!
1.
18

#260000
0!
0.
08

#265000
1!
1.
18

#270000
0!
0.
08

#275000
1!
1.
18

#280000
0!
0.
08

#282000
1%
1+
10
1:
1;
1<
1=
b10 ?

#285000
1!
0)
0*
1.
18
0;
0<
1=
b10 >
b0 ?

#290000
0!
0.
08

#292000
1#
0$
0%
0-
00
07
0:
1=
0@
b101000 A

#295000
1!
1)
1*
0+
1.
18
1;
1<
0=
b0 >
b1 ?

#300000
0!
0.
08

#305000
1!
1.
18
1;
1<
b1 >

#310000
0!
0.
08

#315000
1!
1.
18

#320000
0!
0.
08

#325000
1!
1.
18

#330000
0!
0.
08

#332000
1%
1+
10
1:
1;
1<
1=
b10 ?

#335000
1!
0)
0*
1.
18
0;
0<
1=
b10 >
b0 ?

#340000
0!
0.
08

#345000
1!
1)
1*
0+
1.
18
1;
1<
0=
b0 >
b1 ?

#350000
0!
0.
08

#355000
1!
1+
1.
18
1;
1<
1=
b1 >
b10 ?

#360000
0!
0.
08

#362000
0#
0%
0+
0,
00
b0 5
06
0:
1;
1<
0=
b1 ?

#365000
1!
0(
1.
03
b0 4
18

#370000
0!
0.
08

#375000
1!
1.
18

#380000
0!
0.
08

#382000
1#
1,
b1 5
16
1;
1<
b1010 A

#385000
1!
1&
1'
1.
11
12
b1 4
18

#390000
0!
0.
08

#392000
1%
1+
10
b11 5
1:
1;
1<
1=
b10 ?

#395000
1!
0&
0'
1(
0)
0*
1.
01
02
13
b11 4
18
0;
0<
1=
b10 >
b0 ?

#400000
0!
0.
08

#405000
1!
1)
1*
0+
1.
18
1;
1<
0=
b0 >
b1 ?

#410000
0!
0.
08

#415000
1!
1+
1.
18
1;
1<
1=
b1 >
b10 ?

#420000
0!
0.
08

#422000
0#
0%
0+
0,
00
b0 5
06
0:
1;
1<
0=
b1 ?

#425000
1!
0(
1.
03
b0 4
18

